{
  "name": "Client Amp",
  "initialRoute": "lickityclick/introduction",
  "colors": {
    "light": {
      "brand": "#6B5A8A"
    },
    "dark": {
      "brand": "#9B82C9"
    }
  },
  "navbar": {
    "actions": {
      "primary": {
        "title": "Client Amp",
        "link": "https://clientamp.com"
      }
    }
  },
  "navigation": {
    "products": [
      {
        "product": "LickityClick",
        "icon": "link",
        "tabs": [
          {
            "tab": "Documentation",
            "icon": "book",
            "groups": [
              {
                "group": "Getting Started",
                "icon": "rocket",
                "pages": [
                  {
                    "title": "Introduction",
                    "path": "lickityclick/introduction",
                    "icon": "home"
                  },
                  {
                    "title": "Quickstart",
                    "path": "lickityclick/quickstart",
                    "icon": "zap"
                  }
                ]
              },
              {
                "group": "Product",
                "icon": "star",
                "pages": [
                  {
                    "title": "Features",
                    "path": "lickityclick/features",
                    "icon": "star"
                  },
                  {
                    "title": "Integrations",
                    "path": "lickityclick/integrations",
                    "icon": "plug"
                  }
                ]
              }
            ]
          },
          {
            "tab": "API Reference",
            "icon": "code",
            "groups": [
              {
                "group": "Endpoints",
                "openapi": "lickityclick/api-reference/openapi.yaml",
                "pages": []
              }
            ]
          },
          {
            "tab": "Changelog",
            "icon": "clock",
            "pages": [
              {
                "title": "Release History",
                "path": "lickityclick/changelog",
                "icon": "history"
              }
            ]
          }
        ]
      },
      {
        "product": "HelmNative",
        "icon": "mail",
        "tabs": [
          {
            "tab": "Documentation",
            "icon": "book",
            "groups": [
              {
                "group": "Getting Started",
                "icon": "rocket",
                "pages": [
                  {
                    "title": "Introduction",
                    "path": "helmnative/introduction",
                    "icon": "home"
                  },
                  {
                    "title": "Quickstart",
                    "path": "helmnative/quickstart",
                    "icon": "zap"
                  }
                ]
              },
              {
                "group": "Product",
                "icon": "star",
                "pages": [
                  {
                    "title": "Features",
                    "path": "helmnative/features",
                    "icon": "star"
                  }
                ]
              }
            ]
          },
          {
            "tab": "Changelog",
            "icon": "clock",
            "pages": [
              {
                "title": "Release History",
                "path": "helmnative/changelog",
                "icon": "history"
              }
            ]
          }
        ]
      },
      {
        "product": "TightEdit",
        "icon": "film",
        "tabs": [
          {
            "tab": "Documentation",
            "icon": "book",
            "groups": [
              {
                "group": "Getting Started",
                "icon": "rocket",
                "pages": [
                  {
                    "title": "Introduction",
                    "path": "tightedit/introduction",
                    "icon": "home"
                  },
                  {
                    "title": "Quickstart",
                    "path": "tightedit/quickstart",
                    "icon": "zap"
                  }
                ]
              },
              {
                "group": "Product",
                "icon": "star",
                "pages": [
                  {
                    "title": "Features",
                    "path": "tightedit/features",
                    "icon": "star"
                  }
                ]
              }
            ]
          },
          {
            "tab": "Changelog",
            "icon": "clock",
            "pages": [
              {
                "title": "Release History",
                "path": "tightedit/changelog",
                "icon": "history"
              }
            ]
          }
        ]
      },
      {
        "product": "TightShare",
        "icon": "share-2",
        "tabs": [
          {
            "tab": "Documentation",
            "icon": "book",
            "groups": [
              {
                "group": "Getting Started",
                "icon": "rocket",
                "pages": [
                  {
                    "title": "Introduction",
                    "path": "tightshare/introduction",
                    "icon": "home"
                  },
                  {
                    "title": "Quickstart",
                    "path": "tightshare/quickstart",
                    "icon": "zap"
                  }
                ]
              },
              {
                "group": "Product",
                "icon": "star",
                "pages": [
                  {
                    "title": "Features",
                    "path": "tightshare/features",
                    "icon": "star"
                  }
                ]
              }
            ]
          },
          {
            "tab": "Changelog",
            "icon": "clock",
            "pages": [
              {
                "title": "Release History",
                "path": "tightshare/changelog",
                "icon": "history"
              }
            ]
          }
        ]
      },
      {
        "product": "Droplet Dash",
        "icon": "server",
        "tabs": [
          {
            "tab": "Documentation",
            "icon": "book",
            "groups": [
              {
                "group": "Getting Started",
                "icon": "rocket",
                "pages": [
                  {
                    "title": "Introduction",
                    "path": "droplet-dash/introduction",
                    "icon": "home"
                  },
                  {
                    "title": "Quickstart",
                    "path": "droplet-dash/quickstart",
                    "icon": "zap"
                  }
                ]
              },
              {
                "group": "Product",
                "icon": "star",
                "pages": [
                  {
                    "title": "Features",
                    "path": "droplet-dash/features",
                    "icon": "star"
                  }
                ]
              }
            ]
          },
          {
            "tab": "Changelog",
            "icon": "clock",
            "pages": [
              {
                "title": "Release History",
                "path": "droplet-dash/changelog",
                "icon": "history"
              }
            ]
          }
        ]
      },
      {
        "product": "Sponsor CRM",
        "icon": "handshake",
        "tabs": [
          {
            "tab": "Documentation",
            "icon": "book",
            "groups": [
              {
                "group": "Getting Started",
                "icon": "rocket",
                "pages": [
                  {
                    "title": "Introduction",
                    "path": "sponsor-crm/introduction",
                    "icon": "home"
                  },
                  {
                    "title": "Quickstart",
                    "path": "sponsor-crm/quickstart",
                    "icon": "zap"
                  }
                ]
              },
              {
                "group": "Product",
                "icon": "star",
                "pages": [
                  {
                    "title": "Features",
                    "path": "sponsor-crm/features",
                    "icon": "star"
                  }
                ]
              }
            ]
          },
          {
            "tab": "Changelog",
            "icon": "clock",
            "pages": [
              {
                "title": "Release History",
                "path": "sponsor-crm/changelog",
                "icon": "history"
              }
            ]
          }
        ]
      },
      {
        "product": "DS Hub API",
        "icon": "database",
        "tabs": [
          {
            "tab": "Documentation",
            "icon": "book",
            "groups": [
              {
                "group": "Getting Started",
                "icon": "rocket",
                "pages": [
                  {
                    "title": "Introduction",
                    "path": "ds-hub-api/introduction",
                    "icon": "home"
                  },
                  {
                    "title": "Quickstart",
                    "path": "ds-hub-api/quickstart",
                    "icon": "zap"
                  }
                ]
              },
              {
                "group": "Product",
                "icon": "star",
                "pages": [
                  {
                    "title": "Features",
                    "path": "ds-hub-api/features",
                    "icon": "star"
                  }
                ]
              }
            ]
          },
          {
            "tab": "Changelog",
            "icon": "clock",
            "pages": [
              {
                "title": "Release History",
                "path": "ds-hub-api/changelog",
                "icon": "history"
              }
            ]
          }
        ]
      },
      {
        "product": "Flow",
        "icon": "check-square",
        "tabs": [
          {
            "tab": "Documentation",
            "icon": "book",
            "groups": [
              {
                "group": "Getting Started",
                "icon": "rocket",
                "pages": [
                  {
                    "title": "Introduction",
                    "path": "flow/introduction",
                    "icon": "home"
                  },
                  {
                    "title": "Quickstart",
                    "path": "flow/quickstart",
                    "icon": "zap"
                  }
                ]
              },
              {
                "group": "Product",
                "icon": "star",
                "pages": [
                  {
                    "title": "Features",
                    "path": "flow/features",
                    "icon": "star"
                  }
                ]
              }
            ]
          },
          {
            "tab": "Changelog",
            "icon": "clock",
            "pages": [
              {
                "title": "Release History",
                "path": "flow/changelog",
                "icon": "history"
              }
            ]
          }
        ]
      },
      {
        "product": "Thumbnail Automation Tool",
        "icon": "image",
        "tabs": [
          {
            "tab": "Documentation",
            "icon": "book",
            "groups": [
              {
                "group": "Getting Started",
                "icon": "rocket",
                "pages": [
                  {
                    "title": "Introduction",
                    "path": "thumbnail-automation-tool/introduction",
                    "icon": "home"
                  },
                  {
                    "title": "Quickstart",
                    "path": "thumbnail-automation-tool/quickstart",
                    "icon": "zap"
                  }
                ]
              },
              {
                "group": "Product",
                "icon": "star",
                "pages": [
                  {
                    "title": "Features",
                    "path": "thumbnail-automation-tool/features",
                    "icon": "star"
                  }
                ]
              }
            ]
          },
          {
            "tab": "Changelog",
            "icon": "clock",
            "pages": [
              {
                "title": "Release History",
                "path": "thumbnail-automation-tool/changelog",
                "icon": "history"
              }
            ]
          }
        ]
      },
      {
        "product": "Mac-First Course Publisher",
        "icon": "laptop",
        "tabs": [
          {
            "tab": "Documentation",
            "icon": "book",
            "groups": [
              {
                "group": "Getting Started",
                "icon": "rocket",
                "pages": [
                  {
                    "title": "Introduction",
                    "path": "mac-first-course-publisher/introduction",
                    "icon": "home"
                  },
                  {
                    "title": "Quickstart",
                    "path": "mac-first-course-publisher/quickstart",
                    "icon": "zap"
                  }
                ]
              },
              {
                "group": "Product",
                "icon": "star",
                "pages": [
                  {
                    "title": "Features",
                    "path": "mac-first-course-publisher/features",
                    "icon": "star"
                  }
                ]
              }
            ]
          },
          {
            "tab": "Changelog",
            "icon": "clock",
            "pages": [
              {
                "title": "Release History",
                "path": "mac-first-course-publisher/changelog",
                "icon": "history"
              }
            ]
          }
        ]
      },
      {
        "product": "SharedCore",
        "icon": "package",
        "tabs": [
          {
            "tab": "Documentation",
            "icon": "book",
            "groups": [
              {
                "group": "Overview",
                "icon": "info",
                "pages": [
                  {
                    "title": "Introduction",
                    "path": "shared-core/introduction",
                    "icon": "home"
                  },
                  {
                    "title": "Modules",
                    "path": "shared-core/modules",
                    "icon": "layers"
                  },
                  {
                    "title": "Integration",
                    "path": "shared-core/integration",
                    "icon": "share-2"
                  }
                ]
              },
              {
                "group": "Modules",
                "icon": "package",
                "pages": [
                  {
                    "title": "AIProvider",
                    "path": "shared-core/ai-provider",
                    "icon": "cpu"
                  },
                  {
                    "title": "Design System",
                    "path": "shared-core/design-system",
                    "icon": "palette"
                  },
                  {
                    "title": "KeychainHelper",
                    "path": "shared-core/keychain-helper",
                    "icon": "key"
                  },
                  {
                    "title": "Networking",
                    "path": "shared-core/networking",
                    "icon": "wifi"
                  }
                ]
              }
            ]
          },
          {
            "tab": "Changelog",
            "icon": "clock",
            "pages": [
              {
                "title": "Release History",
                "path": "shared-core/changelog",
                "icon": "history"
              }
            ]
          }
        ]
      },
      {
        "product": "Naming Program",
        "icon": "tag",
        "tabs": [
          {
            "tab": "Documentation",
            "icon": "book",
            "groups": [
              {
                "group": "Strategy",
                "icon": "target",
                "pages": [
                  {
                    "title": "Naming Strategy",
                    "path": "naming-program/strategy",
                    "icon": "file-text"
                  },
                  {
                    "title": "Screening Checklist",
                    "path": "naming-program/checklist",
                    "icon": "check-square"
                  },
                  {
                    "title": "Candidate Names",
                    "path": "naming-program/candidates",
                    "icon": "list"
                  }
                ]
              }
            ]
          }
        ]
      }
    ]
  }
}